jupyterlab_legos_ui/__init__.py
jupyterlab_legos_ui/_version.py
jupyterlab_legos_ui/labextension/package.json
jupyterlab_legos_ui/labextension/static/549.06ef95e33629f743eb22.js
jupyterlab_legos_ui/labextension/static/549.444b40af7f8504d8eada.js
jupyterlab_legos_ui/labextension/static/549.5a64f04763086207b9b8.js
jupyterlab_legos_ui/labextension/static/549.768f468d4cf73c359d41.js
jupyterlab_legos_ui/labextension/static/549.d9c8ceded5dee547062e.js
jupyterlab_legos_ui/labextension/static/568.3bda902f2a408c7763f3.js
jupyterlab_legos_ui/labextension/static/568.99124f7e7e84a1b04718.js
jupyterlab_legos_ui/labextension/static/568.a307a823a6fdd3a93e81.js
jupyterlab_legos_ui/labextension/static/568.a30ce9dbf0d6ea5d7301.js
jupyterlab_legos_ui/labextension/static/568.a98c8ca6adf3e33b35eb.js
jupyterlab_legos_ui/labextension/static/remoteEntry.19a3d159124ee88f70d7.js
jupyterlab_legos_ui/labextension/static/remoteEntry.3d40faf0c60617b7a5fb.js
jupyterlab_legos_ui/labextension/static/remoteEntry.468f121c02f81b5c3156.js
jupyterlab_legos_ui/labextension/static/remoteEntry.4e75884f994242563b0a.js
jupyterlab_legos_ui/labextension/static/remoteEntry.5eb69d810aea54fd3e40.js
jupyterlab_legos_ui/labextension/static/remoteEntry.6081ead79c2d57b9f4da.js
jupyterlab_legos_ui/labextension/static/remoteEntry.6090313578ecf6e4a377.js
jupyterlab_legos_ui/labextension/static/remoteEntry.637fecaceb588e075e97.js
jupyterlab_legos_ui/labextension/static/remoteEntry.6662937f175d8fe7a694.js
jupyterlab_legos_ui/labextension/static/remoteEntry.b7979aa38bd557d318dd.js
jupyterlab_legos_ui/labextension/static/remoteEntry.c7ec9e98d0481c05e259.js
jupyterlab_legos_ui/labextension/static/remoteEntry.fa1625be941f70598937.js
jupyterlab_legos_ui/labextension/static/style.js
jupyterlab_legos_ui/labextension/themes/@dunovank/jupyterlab_legos_ui/index.css
jupyterlab_legos_ui/labextension/themes/@dunovank/jupyterlab_legos_ui/index.js
jupyterlab_legos_ui-0.2.2.dist-info/LICENSE
jupyterlab_legos_ui-0.2.2.dist-info/METADATA
jupyterlab_legos_ui-0.2.2.dist-info/WHEEL
jupyterlab_legos_ui-0.2.2.dist-info/top_level.txt
jupyterlab_legos_ui-0.2.2.dist-info/RECORD
