Metadata-Version: 2.1
Name: jupyterlab-legos-ui
Version: 0.2.2
Summary: legos light ui and syntax theme for jupyterlab
Home-page: https://github.com/dunovank/jupyterlab_legos_ui
Author: Kyle Dunovan
License: BSD-3-Clause
Keywords: Jupyter,JupyterLab
Platform: Linux
Platform: Mac OS X
Platform: Windows
Classifier: License :: OSI Approved :: BSD License
Classifier: Programming Language :: Python
Classifier: Programming Language :: Python :: 3
Classifier: Programming Language :: Python :: 3.6
Classifier: Programming Language :: Python :: 3.7
Classifier: Programming Language :: Python :: 3.8
Classifier: Programming Language :: Python :: 3.9
Classifier: Framework :: Jupyter
Requires-Python: >=3.6
License-File: LICENSE
Requires-Dist: jupyterlab (==3.*,>=3.0.0)
Requires-Dist: nbconvert (==5.6.1)
Requires-Dist: jedi (==0.17.2)
